dreamhack/__init__.py
dreamhack/colorcodes.py
dreamhack/encryption.py
dreamhack/logging.py
dreamhack/windows.py
dreamhack/zipfiles.py
dreamhack-1.0.1.dist-info/METADATA
dreamhack-1.0.1.dist-info/WHEEL
dreamhack-1.0.1.dist-info/top_level.txt
dreamhack-1.0.1.dist-info/RECORD
