Metadata-Version: 2.1
Name: dreamhack
Version: 1.0.1
Summary: The ultimate PyPi package for cyber-security and many other things.
Author: Jack Burr
Author-email: BurrJ22@Outlook.com
Keywords: python,windows
Classifier: Programming Language :: Python :: 3
Classifier: Operating System :: Microsoft :: Windows
Requires-Dist: cryptography
Requires-Dist: tqdm
Requires-Dist: setuptools
